examples/__init__.py
examples/baidu_index_best_practice.py
examples/test_baidu_index.py
examples/test_baidu_login.py
examples/test_baidu_search.py
examples/test_tianyancha.py
qdata/__init__.py
qdata/errors.py
qdata/utils.py
qdata/baidu_index/__init__.py
qdata/baidu_index/baidu_index.py
qdata/baidu_index/common.py
qdata/baidu_index/config.py
qdata/baidu_index/extended_baidu_index.py
qdata/baidu_index/live_baidu_index.py
qdata/baidu_login/__init__.py
qdata/baidu_login/common.py
qdata/baidu_login/config.py
qdata/baidu_login/qr_login.py
qdata/baidu_search/__init__.py
qdata/baidu_search/baidu_search.py
qdata/tianyancha/__init__.py
qdata/tianyancha/company_count.py
qdata/tianyancha/company_filter_options.py
qdata/tianyancha/base_datas/__init__.py
qdata/tianyancha/base_datas/area.py
qdata/tianyancha/base_datas/category.py
qdata-0.2.4.dist-info/LICENSE
qdata-0.2.4.dist-info/METADATA
qdata-0.2.4.dist-info/WHEEL
qdata-0.2.4.dist-info/top_level.txt
qdata-0.2.4.dist-info/RECORD
