Metadata-Version: 2.1
Name: qdata
Version: 0.2.4
Summary: Python SDK for getting data quickly
Home-page: https://github.com/longxiaofei/spider-BaiduIndex
Author: longxiaofei
Author-email: libra.19951002@gmail.com
License: UNKNOWN
Keywords: data sdk
Platform: UNKNOWN
Classifier: License :: OSI Approved :: MIT License
Classifier: Programming Language :: Python :: 3
Classifier: Programming Language :: Python :: 3.6
Classifier: Programming Language :: Python :: 3.7
Classifier: Programming Language :: Python :: 3.8
Classifier: Programming Language :: Python
Requires-Dist: requests (>=2.19.1)
Requires-Dist: matplotlib (>=3.3.4)
Requires-Dist: pycryptodome (>=3.10.1)
